spectron/Field.py
spectron/MaxDict.py
spectron/__init__.py
spectron/cli.py
spectron/data_types.py
spectron/ddl.py
spectron/merge.py
spectron/parse_date.py
spectron/reserved.py
spectron/write_ddl.py
spectron-0.4.8.dist-info/LICENSE
spectron-0.4.8.dist-info/METADATA
spectron-0.4.8.dist-info/WHEEL
spectron-0.4.8.dist-info/entry_points.txt
spectron-0.4.8.dist-info/top_level.txt
spectron-0.4.8.dist-info/RECORD
