Metadata-Version: 2.1
Name: spectron
Version: 0.4.8
Summary: AWS Redshift Spectrum utilities.
Home-page: https://github.com/j4c0bs/spectron
Author: Jeremy Jacobs
Author-email: pub@j4c0bs.net
License: UNKNOWN
Platform: UNKNOWN
Classifier: Intended Audience :: Developers
Classifier: License :: OSI Approved :: MIT License
Classifier: Programming Language :: Python :: 3.7
Classifier: Programming Language :: Python :: 3.8
Requires-Python: >=3.7
Requires-Dist: black (>=19.10b0)
Requires-Dist: pendulum (>=1.4.4)
Provides-Extra: json
Requires-Dist: ujson (==1.35) ; extra == 'json'
